{"id":"nb1783758923242667","mode":"blog","ok":true,"text":"모래시계 그 선율부터 리베르탱고까지, 9월의 브런치 콘서트 <현 위로 흐르는 계절 : 열정과 고독 사이>\n\n9월 3일 목요일, 오전 11시. 여수 예울마루 대극장에서 브런치 콘서트를 한 편 준비했습니다. 2013년부터 이어 온 예울마루의 오전 공연인데, 이번 프로그램 이름이 <현 위로 흐르는 계절 : 열정과 고독 사이>예요. 무대를 채우는 악기는 넷 — 클래식 기타, 바이올린, 퍼커션, 더블베이스. 기타를 가운데 두고 브라질 보사노바에서 스페인을 지나 아르헨티나 탱고까지, 현(絃) 위를 건너가는 80분입니다. ☕\n\n연주자들부터 소개할게요.\n클래식 기타리스트 김진택 님은 이번 무대에서 연주와 해설을 함께 맡습니다. 영화 <건축학개론> OST와 비올리스트 리처드 용재 오닐의 2집 <라크리메> 작업에 편곡·연주로 참여했고, 지금은 한국예술종합학교·안양대 겸임교수이자 기타그룹 '피에스타'의 리더예요. 곡 사이사이 해설을 붙여 주니, 클래식 기타가 처음이어도 어렵지 않게 따라오실 수 있습니다.\n바이올리니스트 윤염광 님은 미국 맨해튼 음대에서 공부하고 카네기홀을 비롯한 해외 무대에서 연 100회 넘게 연주해 온 분으로, 지금은 서초교향악단 악장을 맡고 있어요.\n퍼커셔니스트 파코드 진 님은 아프로쿠반부터 브라질, 페루, 스페인 플라멩코까지 아우르는, 국내에 흔치 않은 라틴 퍼커션 전문 연주자입니다.\n더블베이스 진영환 님은 미국에서 베이스를 전공하고 라틴 재즈 앨범 <El Primer>를 낸 연주자로, 지금은 중부대학교 실용음악과 교수로 있고요.\n\n프로그램은 세 파트예요. 곡마다 한 줄씩만 붙여 봅니다.\n\nPART 1\n· 루이스 본파 '리오를 거닐며' — 제목 그대로 리우데자네이루의 거리를 거니는 듯한 브라질 기타 곡으로 첫 문을 엽니다.\n· 타레가 '알함브라 궁전의 추억 & 대왈츠' — 타레가가 짝사랑을 거절당한 뒤 그라나다 알함브라 궁전의 분수를 바라보며 썼다는 곡이에요. 쉼 없이 떨리는 트레몰로가 물방울처럼 이어집니다. 함께 연주하는 '대왈츠'는 그 유명한 노키아 휴대폰 벨소리의 원곡이기도 하고요.\n· 후안 질베르토 '이파네마의 소녀' — 1960년대 리우 이파네마 해변의 실제 한 소녀에게서 시작된, 지금까지 수없이 다시 불린 보사노바의 대표곡입니다.\n· 딜레르만두 헤이스 '바이아의 여인' — 브라질 정서가 물씬한 기타 소품으로 1부를 나른하게 닫습니다.\n\nPART 2\n· 마스네 '타이스의 명상곡' — 오페라 <타이스>의 막간에 흐르던 그 선율을 기타·퍼커션·베이스 편성으로 들려줍니다. 제목의 '고독' 쪽에 가장 가까운 곡이에요.\n· 피아졸라 '탱고의 역사' — 탱고가 뒷골목 음악에서 콘서트홀 음악으로 걸어온 100년을, 피아졸라가 네 장면으로 그린 곡입니다.\n· 파가니니 '소나타 6번' — 1995년 드라마 <모래시계> '혜린의 테마'로 온 국민이 기억하는 바로 그 멜로디죠. 바이올린과 기타 단 두 대로 연주해요. 저는 이 곡 리허설부터 챙겨 볼 생각이에요.\n\nPART 3\n· 치코 노바로 '당신과 함께' — 아르헨티나에서 오래 사랑받아 온 노래로 3부를 나긋하게 엽니다.\n· 그라나도스 '안달루사의 여인' — 스페인 남부의 볕이 그대로 담긴 춤곡입니다.\n· 피아졸라 '리베르탱고' — '자유(리베르타드)'와 '탱고'를 합친 제목처럼, 전통 탱고를 박차고 나온 곡이에요. 네 악기가 한꺼번에 달려 나가며 공연을 맺습니다.\n\n브런치 콘서트인 만큼, 공연을 보고 근처에서 늦은 아침을 즐길 방법도 챙겨 뒀어요. 공연 티켓 2매에 정쿡 웅천점 식사(2인)를 묶은 '브런치 패키지'가 특별가 70,000원이고, 혼자 오신다면 공연 티켓에 기획전시 <숨 쉬는 SUM> 관람까지 더한 '전시 패키지'가 20,000원이라 전석 가격 그대로 전시까지 보실 수 있습니다. 할인은 홈페이지 회원 10%, 20인 이상 단체 20%, 복지·국가유공자 대상 최대 50%까지 있어요.\n\n평일 오전, 커피 한 잔 들고 기타 선율에 기대는 80분. 9월의 시작을 이렇게 열어 보셔도 좋겠습니다. 🎸\n\n· 일시 | 2026. 9. 3(목) 오전 11시\n· 장소 | GS칼텍스 예울마루 대극장\n· 관람 | 약 80분 · 초등학생 이상\n· 티켓 | 전석 20,000원\n· 예매 | 예울마루 홈페이지 / 티켓링크 · 문의 | 1544-7669","tags":["브런치콘서트","현위로흐르는계절","예울마루브런치콘서트","기타리스트김진택","바이올리니스트윤염광","퍼커셔니스트파코드진","베이시스트진영환","클래식기타연주회","리베르탱고","알함브라궁전의추억","예울마루","GS칼텍스예울마루","여수예울마루","예울마루대극장","여수공연장","여수여행","여수가볼만한곳","여수주말나들이","여수당일치기","여수문화생활","여수여행코스","순천데이트","순천가볼만한곳","광양가볼만한곳","주말데이트","아이와문화생활","부모님선물","9월공연","가을음악회","클래식공연추천"],"research":"- 클래식 기타리스트 김진택은 영화 <건축학개론> OST와 리처드 용재 오닐 2집 <라크리메> 편곡·연주에 참여했다 (싱글리스트 slist.kr)\n- 김진택은 한국예술종합학교·안양대 겸임교수이자 기타그룹 피에스타·트리오 라움의 리더다 (예술의전당 sac.or.kr, 싱글리스트)\n- 파가니니 '바이올린과 기타를 위한 소나타 6번'은 1995년 SBS 드라마 <모래시계> '혜린의 테마'로 쓰였다 (컬처램프 culturelamp.kr, 벅스 bugs.co.kr)\n- 드라마 <모래시계>(1995, SBS)는 최고 시청률 약 64.5%를 기록한 대히트작이다 (park5611 블로그 등, 널리 보도됨)\n- 타레가 <알함브라 궁전의 추억>(1896)은 짝사랑 거절 뒤 그라나다 알함브라에서 영감받아 트레몰로 주법으로 썼다는 일화가 전한다 (나무위키, SpainAgain)\n- 타레가 <대왈츠(Gran Vals)>(1902)의 13~16마디가 노키아 휴대폰 벨소리(노키아 튠)의 원곡이다 (위키백과 '노키아 튠', 나무위키)\n- <이파네마의 소녀>는 1962년 조빔·비니시우스가 리우 이파네마의 실제 소녀 엘로이자 피녜이루(1945년생)에게서 영감받아 만든 보사노바다 (위키백과, 서울신문 seoul.co.kr)\n- 피아졸라 <리베르탱고>(1974, 밀라노)는 '리베르타드(자유)+탱고' 합성어로, 그가 전통 탱고에서 누에보 탱고로 전환했음을 상징한다 (위키백과, 나무위키)","ts":"2026-07-11T08:44:30.365Z"}